hlpl_graphics/__init__.py
hlpl_graphics/__main__.py
hlpl_graphics/setup.cfg
hlpl_graphics-1.0.0.dist-info/LICENSE
hlpl_graphics-1.0.0.dist-info/METADATA
hlpl_graphics-1.0.0.dist-info/WHEEL
hlpl_graphics-1.0.0.dist-info/entry_points.txt
hlpl_graphics-1.0.0.dist-info/top_level.txt
hlpl_graphics-1.0.0.dist-info/RECORD
